ukaddresskit/__init__.py
ukaddresskit/cli.py
ukaddresskit/locality.py
ukaddresskit/models.py
ukaddresskit/parser.py
ukaddresskit/pipeline.py
ukaddresskit/postcode.py
ukaddresskit/tokens.py
ukaddresskit/data/lookups/counties.csv
ukaddresskit/data/lookups/localities.csv
ukaddresskit/data/lookups/locality_to_town.csv
ukaddresskit/data/lookups/outcode_to_county.csv
ukaddresskit/data/lookups/postcode_district_to_town.csv
ukaddresskit/data/lookups/postcode_property_mix.csv
ukaddresskit/data/lookups/postcode_to_locality.csv
ukaddresskit/data/lookups/postcode_to_streets.csv
ukaddresskit/data/lookups/synonyms.csv
ukaddresskit/data/models/base.crfsuite
ukaddresskit-0.0.5.dist-info/METADATA
ukaddresskit-0.0.5.dist-info/WHEEL
ukaddresskit-0.0.5.dist-info/entry_points.txt
ukaddresskit-0.0.5.dist-info/licenses/LICENSE
ukaddresskit-0.0.5.dist-info/RECORD
