Metadata-Version: 2.4
Name: ukaddresskit
Version: 0.0.5
Summary: UK address utility based on machine learning and optimised search to parse, standardise, and compare addresses.
Project-URL: Homepage, https://github.com/reachusama/ukaddresskit
Project-URL: Issues, https://github.com/reachusama/ukaddresskit/issues
Author-email: Usama Shahid <usamashahid.us8@gmail.com>
Maintainer-email: Usama Shahid <usamashahid.us8@gmail.com>
License: Copyright (c) 2018 The Python Packaging Authority
License-File: LICENSE
Keywords: NER,UK,addresses,parsing,postcode
Classifier: Development Status :: 3 - Alpha
Classifier: Programming Language :: Python
Requires-Python: >=3.10
Requires-Dist: lxml<6,>=4.9
Requires-Dist: pandas>=2.0.0
Requires-Dist: platformdirs>=4.2.2
Requires-Dist: python-crfsuite<=0.9.11,>=0.9.7
Provides-Extra: dev
Requires-Dist: black; extra == 'dev'
Requires-Dist: isort; extra == 'dev'
Requires-Dist: mypy>=1.10; extra == 'dev'
Requires-Dist: pytest>=7.4; extra == 'dev'
Requires-Dist: ruff>=0.5.6; extra == 'dev'
Provides-Extra: train
Requires-Dist: scikit-learn>=1.3; extra == 'train'
Requires-Dist: sklearn-crfsuite>=0.3.6; extra == 'train'
